README.md
setup.cfg
setup.py
addresslib/__init__.py
addresslib/compat.py
python_addresslib.egg-info/PKG-INFO
python_addresslib.egg-info/SOURCES.txt
python_addresslib.egg-info/dependency_links.txt
python_addresslib.egg-info/top_level.txt