Metadata-Version: 1.1
Name: python-addresslib
Version: 1.0.0
Summary: Python email address parsing library
Home-page: https://github.com/alexei/python-addresslib
Author: Alexei
Author-email: hello@alexei.ro
License: UNKNOWN
Download-URL: https://github.com/alexei/python-addresslib/archive/1.0.0.tar.gz
Keywords: email address parser
Platform: UNKNOWN
